pulumi_postgresql/__init__.py
pulumi_postgresql/_inputs.py
pulumi_postgresql/_utilities.py
pulumi_postgresql/database.py
pulumi_postgresql/default_privileg.py
pulumi_postgresql/default_privileges.py
pulumi_postgresql/extension.py
pulumi_postgresql/function.py
pulumi_postgresql/get_schemas.py
pulumi_postgresql/get_sequences.py
pulumi_postgresql/get_tables.py
pulumi_postgresql/grant.py
pulumi_postgresql/grant_role.py
pulumi_postgresql/outputs.py
pulumi_postgresql/physical_replication_slot.py
pulumi_postgresql/provider.py
pulumi_postgresql/publication.py
pulumi_postgresql/pulumi-plugin.json
pulumi_postgresql/py.typed
pulumi_postgresql/replication_slot.py
pulumi_postgresql/role.py
pulumi_postgresql/schema.py
pulumi_postgresql/security_label.py
pulumi_postgresql/server.py
pulumi_postgresql/subscription.py
pulumi_postgresql/user_mapping.py
pulumi_postgresql/config/__init__.py
pulumi_postgresql/config/__init__.pyi
pulumi_postgresql/config/outputs.py
pulumi_postgresql/config/vars.py
pulumi_postgresql-3.16.1.dist-info/METADATA
pulumi_postgresql-3.16.1.dist-info/WHEEL
pulumi_postgresql-3.16.1.dist-info/top_level.txt
pulumi_postgresql-3.16.1.dist-info/RECORD
